LICENSE
MANIFEST.in
README.md
requirements.txt
requirements_test.txt
setup.cfg
setup.py
hybridcontents/__init__.py
hybridcontents/api_utils.py
hybridcontents/hybridmanager.py
hybridcontents.egg-info/PKG-INFO
hybridcontents.egg-info/SOURCES.txt
hybridcontents.egg-info/dependency_links.txt
hybridcontents.egg-info/requires.txt
hybridcontents.egg-info/top_level.txt
hybridcontents.egg-info/zip-safe
hybridcontents/tests/__init__.py
hybridcontents/tests/test_hybrid_manager.py
hybridcontents/tests/testing_utils.py